pyd3m2o/__init__.py
pyd3m2o-0.0.1.dist-info/METADATA
pyd3m2o-0.0.1.dist-info/WHEEL
pyd3m2o-0.0.1.dist-info/licenses/LICENSE
pyd3m2o-0.0.1.dist-info/RECORD
