Metadata-Version: 2.4
Name: pyd3m2o
Version: 0.0.1
Summary: Dynamic Multi-Modal Multi-Objective Optimization in Python (pyd3m2o).
Project-URL: Homepage, https://github.com/dynoptimization/pyd3m2o
Project-URL: Repository, https://github.com/dynoptimization/pyd3m2o
Project-URL: Documentation, https://dynoptimization.github.io/pyd3m2o/
Project-URL: Source, https://github.com/dynoptimization/pyd3m2o
Project-URL: Issues, https://github.com/dynoptimization/pyd3m2o/issues
Project-URL: Changelog, https://github.com/dynoptimization/pyd3m2o/releases
Author-email: DynOpt <dynoptimization@gmail.com>
Maintainer-email: DynOpt <dynoptimization@gmail.com>
License: GPL-3.0-or-later
License-File: LICENSE
Keywords: Dynamic Multi-Modal Multi-objective Optimization,Python
Classifier: Operating System :: OS Independent
Classifier: Programming Language :: Python
Classifier: Programming Language :: Python :: 3
Classifier: Programming Language :: Python :: 3.12
Classifier: Programming Language :: Python :: 3.13
Classifier: Programming Language :: Python :: 3.14
Classifier: Topic :: Scientific/Engineering
Classifier: Topic :: Scientific/Engineering :: Artificial Intelligence
Classifier: Topic :: Scientific/Engineering :: Mathematics
Requires-Python: >=3.12
Requires-Dist: matplotlib>=3.10.8
Requires-Dist: mpmath>=1.3.0
Requires-Dist: numpy>=2.4.0
Requires-Dist: pandas>=2.3.3
Requires-Dist: psutil>=7.2.0
Requires-Dist: scikit-learn>=1.8.0
Requires-Dist: scikit-posthocs>=0.11.4
Requires-Dist: scipy>=1.16.3
Requires-Dist: seaborn>=0.13.2
Requires-Dist: statsmodels>=0.14.6
Requires-Dist: tabulate>=0.9.0
Requires-Dist: torch>=2.9.1
